systemdlogger/__init__.py
systemdlogger/aws.py
systemdlogger/cloudwatch.py
systemdlogger/elasticsearch.py
systemdlogger/journal.py
systemdlogger/log.py
systemdlogger/plugin.py
systemdlogger/runner.py
systemdlogger/systemdlogger.py
systemdlogger-0.2.3.dist-info/DESCRIPTION.rst
systemdlogger-0.2.3.dist-info/METADATA
systemdlogger-0.2.3.dist-info/RECORD
systemdlogger-0.2.3.dist-info/WHEEL
systemdlogger-0.2.3.dist-info/entry_points.txt
systemdlogger-0.2.3.dist-info/metadata.json
systemdlogger-0.2.3.dist-info/top_level.txt
